atmwithdrawal/__init__.py
atmwithdrawal/app.py
atmwithdrawal/atmwithdrawalcheck.py
sourishatmwithdrawalconcept-1.7.dist-info/licenses/LICENSE
sourishatmwithdrawalconcept-1.7.dist-info/METADATA
sourishatmwithdrawalconcept-1.7.dist-info/WHEEL
sourishatmwithdrawalconcept-1.7.dist-info/top_level.txt
sourishatmwithdrawalconcept-1.7.dist-info/RECORD
