Metadata-Version: 2.4
Name: SourishATMWithdrawalConcept
Version: 1.7
Summary: This is the homepage of this project. 
License-File: LICENSE
Dynamic: license-file
Dynamic: summary
